wcget/__init__.py
wcget/wcget.py
wcget-0.0.1.dist-info/LICENSE
wcget-0.0.1.dist-info/METADATA
wcget-0.0.1.dist-info/WHEEL
wcget-0.0.1.dist-info/entry_points.txt
wcget-0.0.1.dist-info/top_level.txt
wcget-0.0.1.dist-info/RECORD
